cvd_color_palette_generator/__init__.py
cvd_color_palette_generator/aux_functions.py
cvd_color_palette_generator/binary.py
cvd_color_palette_generator/categorical.py
cvd_color_palette_generator/diverging.py
cvd_color_palette_generator/module1.py
cvd_color_palette_generator/module2.py
cvd_color_palette_generator/sequential.py
tests/__init__.py
tests/test_aux_functions.py
tests/test_module1.py
cvd_color_palette_generator-0.1.dist-info/LICENSE
cvd_color_palette_generator-0.1.dist-info/METADATA
cvd_color_palette_generator-0.1.dist-info/WHEEL
cvd_color_palette_generator-0.1.dist-info/top_level.txt
cvd_color_palette_generator-0.1.dist-info/RECORD
